wiktfinnish/__init__.py
wiktfinnish/formnames.py
wiktfinnish/inflect.py
wiktfinnish/nounspecs.py
wiktfinnish/verbspecs.py
wiktfinnish-0.1.4.dist-info/LICENSE
wiktfinnish-0.1.4.dist-info/METADATA
wiktfinnish-0.1.4.dist-info/WHEEL
wiktfinnish-0.1.4.dist-info/top_level.txt
wiktfinnish-0.1.4.dist-info/RECORD
