Metadata-Version: 2.1
Name: wiktfinnish
Version: 0.1.4
Summary: Finnish morphology (including verb forms, comparatives, cases, possessives, clitics)
Home-page: https://clausal.com
Author: Tatu Ylonen
Author-email: ylo@clausal.com
License: MIT
Download-URL: https://github.com/tatuylonen/wiktfinnish
Platform: UNKNOWN
Classifier: Development Status :: 3 - Alpha
Classifier: Intended Audience :: Developers
Classifier: Intended Audience :: Science/Research
Classifier: License :: OSI Approved :: MIT License
Classifier: Natural Language :: Finnish
Classifier: Operating System :: OS Independent
Classifier: Operating System :: POSIX :: Linux
Classifier: Programming Language :: Python
Classifier: Programming Language :: Python :: 3.6
Classifier: Programming Language :: Python :: 3.7
Classifier: Programming Language :: Python :: 3 :: Only
Classifier: Topic :: Text Processing
Classifier: Topic :: Text Processing :: Linguistic
